c8_target_c8collection/__init__.py
c8_target_c8collection/main.py
c8_target_c8collection-0.0.25.dist-info/LICENSE
c8_target_c8collection-0.0.25.dist-info/METADATA
c8_target_c8collection-0.0.25.dist-info/WHEEL
c8_target_c8collection-0.0.25.dist-info/entry_points.txt
c8_target_c8collection-0.0.25.dist-info/top_level.txt
c8_target_c8collection-0.0.25.dist-info/RECORD
