Metadata-Version: 2.1
Name: c8-target-c8collection
Version: 0.0.25
Summary: Singer.io target for writing to C8DB collection
Author-email: Macrometa <info@macrometa.co>
License: 
Project-URL: Homepage, https://www.macrometa.com/
Project-URL: Bug Tracker, https://github.com/Macrometacorp/c8-target-c8collection/issues
Keywords: ELT,Connectors,Workflows,Macrometa,C8DB,Target
Classifier: Programming Language :: Python :: 3
Classifier: Programming Language :: Python :: 3.7
Classifier: Operating System :: OS Independent
Requires-Python: >=3.7
License-File: LICENSE
Requires-Dist: pipelinewise-singer-python (==1.2.0)
Requires-Dist: adjust-precision-for-schema (==0.3.4)
Requires-Dist: pyc8 (==0.17.1)
Requires-Dist: c8connector (==0.0.10)
